{
  "まいなすいちきゅうだい": 1185,
  "まいなすいちきゅうねん": 1011,
  "じゅういちきろめーとる": 1262,
  "じゅういちきょくおさむ": 1171,
  "じゅうはちきろめーとる": 1521,
  "いちきろめーとるじゃく": 2592,
  "いちきろめーとるはなれ": 1980,
  "にじゅういちきろぐらむ": 1078,
  "にじゅういちにちきょう": 1186,
  "にじゅうはちきろぐらむ": 1478,
  "ごじゅういちきろぐらむ": 1546,
  "ごじゅうはちきろぐらむ": 3577,
  "ろくじゅうごにちきゅう": 2728,
  "はちきろめーとるはなれ": 1034,
  "いちきゅうひとつひとつ": 2288,
  "いちきょくしゅうちゅう": 1025,
  "ちゅうにちきゅうじょう": 1171,
  "ぜんにじゅういちきょく": 1738,
  "いのちきゅうきゅうこう": 1505,
  "かこいいちきろめーとる": 1099,
  "かたちきょういくとおる": 1000,
  "あたりいちきろめーとる": 1674,
  "ちょういちきろめーとる": 1653,
  "ぱーせんとおよびいちき": 1479,
  "(いちきゅうきゅうなな": 1682,
  "(いちきゅうきゅうさん": 1300,
  "(いちきゅうきゅうはち": 1704,
  "(いちきゅうきゅうろく": 1464,
  "(いちきゅうきゅうよん": 1377,
  "じゅういちきろぐらむや": 2034,
  "じゅういちにちきんよう": 2085,
  "じゅうににちきょうどう": 1667,
  "じゅうさんにちきんよう": 2264,
  "じゅうごにちきょうどう": 1738,
  "じゅうろくにちきんよう": 2627,
  "じゅうしちにちきんよう": 1191,
  "じゅうはちにちきんよう": 2088,
  "じゅうはちきん)いずる": 9622,
  "じゅうはちきんさくひん": 1494,
  "じゅうはちきんどうじん": 2890,
  "じゅうくにちきょうどう": 1730,
  "いちきろぐらむちゅうに": 1032,
  "いちきろぐらむいじょう": 4015,
  "いちきろめーとるのえき": 1175,
  "いちきろめーとるいない": 22802,
  "いちきろめーとるさきの": 2113,
  "いちきろめーとるしほう": 1532,
  "いちきろめーとるちてん": 2100,
  "いちきろめーとるてまえ": 1113,
  "いちきろめーとるほどの": 3619,
  "いちきろめーとるていど": 3021,
  "いちきろめーとるはしっ": 1112,
  "いちきろめーとるちかく": 1057,
  "いちきろめーとるばなれ": 1965,
  "ついたちいちきろぐらむ": 1088,
  "いちきょくいちきょくが": 1757,
  "いちきょくいちきょくに": 1437,
  "いちきょくいちきょくの": 1543,
  "いちきょくいちきょくを": 1006,
  "いちきょくをしゅうろく": 1616,
  "にじゅうににちきんよう": 1211,
  "にじゅうさんにちきょう": 1283,
  "にじゅうごにちきんよう": 1791,
  "にじゅうろくにちきょう": 1098,
  "にじゅうしちにちきょう": 1199,
  "にじゅうはちにちきょう": 1067,
  "にじゅうくにちきんよう": 1121,
  "さんじゅうにちきんよう": 1307,
  "はちきゅうしきそうこう": 1042,
  "はちきろぐらむいじょう": 1475,
  "はちきろめーとるちてん": 1900,
  "はちきろめーとるばなれ": 1032,
  "はちきょくをしゅうろく": 1414,
  ":やくいちきろめーとる": 5552,
  "じーえいちきゅー(れん": 2893,
  "じーえいちきゅーのゆび": 3236,
  "じーえいちきゅーのけん": 1154,
  "えむいちきゅういちいち": 1734,
  "えぬえいちけいちきゅう": 1170,
  "てぃーてぃーきちきょく": 1825,
  "、いちきょくいちきょく": 2624,
  "、いちきゅうななきゅう": 1775,
  "、いちきゅうきゅうなな": 4830,
  "、いちきゅうきゅうさん": 3506,
  "、いちきゅうきゅうはち": 5185,
  "、いちきゅうきゅうろく": 4359,
  "、いちきゅうきゅうよん": 3707,
  "、いちきゅうろくきゅう": 1322,
  "、いちきゅうよんきゅう": 1441,
  "、いちきゅういちきゅう": 1294,
  "、ぜんじゅういちきょく": 1059,
  "、しゃくはちきょうしつ": 4268,
  "、やくいちきろめーとる": 3622,
  "、たにまちきゅうちょう": 1535,
  "がじゅういちきろぐらむ": 2163,
  "がやくいちきろめーとる": 1153,
  "てやくいちきろめーとる": 1588,
  "でやくいちきろめーとる": 2726,
  "でやくはちきろめーとる": 1157,
  "にやくいちきろめーとる": 2498,
  "のやくいちきろめーとる": 2057,
  "はいちきゅうきゅういち": 1198,
  "はいちきゅうきゅうなな": 2167,
  "はいちきゅうきゅうさん": 1416,
  "はいちきゅうきゅうはち": 2234,
  "はいちきゅうきゅうろく": 1695,
  "はいちきゅうきゅうよん": 1402,
  "はいちきゅうはちきゅう": 1269,
  "はやくいちきろめーとる": 2194,
  "へやくいちきろめーとる": 1526,
  "らいちきろめーとるほど": 3116,
  "らやくいちきろめーとる": 4957,
  "らやくはちきろめーとる": 1365,
  "りやくいちきろめーとる": 1663,
  "をやくいちきろめーとる": 1053,
  "いちななはちきゅうねん": 1019,
  "いちきゅうれいれいねん": 2850,
  "いちきゅういちれいねん": 3037,
  "いちきゅういちいちねん": 1519,
  "いちきゅういちななねん": 2953,
  "いちきゅういちさんねん": 1523,
  "いちきゅういちはちねん": 2743,
  "いちきゅういちろくねん": 1458,
  "いちきゅういちよんねん": 2200,
  "いちきゅうななれいねん": 3207,
  "いちきゅうなないちねん": 1028,
  "いちきゅうななななねん": 4652,
  "いちきゅうななさんねん": 1152,
  "いちきゅうななはちねん": 1111,
  "いちきゅうななろくねん": 4584,
  "いちきゅうななよんねん": 4653,
  "いちきゅうさんれいねん": 1978,
  "いちきゅうさんいちねん": 3417,
  "いちきゅうさんななねん": 1035,
  "いちきゅうさんさんねん": 3317,
  "いちきゅうさんはちねん": 3441,
  "いちきゅうさんろくねん": 3189,
  "いちきゅうさんよんねん": 2814,
  "いちきゅうきゅうにねん": 1871,
  "いちきゅうきゅうごねん": 3404,
  "いちきゅうにきゅうねん": 3559,
  "いちきゅうごきゅうねん": 3853,
  "いちきゅうはちれいねん": 3123,
  "いちきゅうはちいちねん": 1038,
  "いちきゅうはちななねん": 1394,
  "いちきゅうはちさんねん": 1128,
  "いちきゅうはちはちねん": 1447,
  "いちきゅうはちろくねん": 1258,
  "いちきゅうはちよんねん": 5868,
  "いちきゅうろくれいねん": 3191,
  "いちきゅうろくいちねん": 4108,
  "いちきゅうろくななねん": 1008,
  "いちきゅうろくさんねん": 4150,
  "いちきゅうろくはちねん": 1177,
  "いちきゅうろくろくねん": 4462,
  "いちきゅうろくよんねん": 1047,
  "いちきゅうよんれいねん": 1136,
  "いちきゅうよんいちねん": 1205,
  "いちきゅうよんななねん": 1283,
  "いちきゅうよんさんねん": 1000,
  "いちきゅうよんはちねん": 1264,
  "いちきゅうよんろくねん": 1353,
  "いちきゅうよんよんねん": 1447,
  "いちはちきゅうれいねん": 1503,
  "いちはちきゅうななねん": 1032,
  "いちはちきゅうはちねん": 1258,
  "いちはちきゅうろくねん": 1073,
  "いちはちきゅうよんねん": 1172,
  "いちきょうかいしんじゃ": 3789,
  "いちきょうかい(みつる": 2218,
  "いちきょうかいのきょう": 1451,
  "いちきゅういちきゅうに": 1402,
  "いっぱんじゅうはちきん": 1216,
  "きゅうはちきゅうねんに": 1705,
  "きゅうはちきゅうねんの": 1402,
  "ひとちきゅうかんきょう": 1122,
  "かいちきゅうかんきょう": 1918,
  "ぜんじゅういちきょくを": 1257,
  "ぜんこくちきゅうあつし": 1380,
  "こうえんりょくちきょう": 2625,
  "うちちきゅうかんきょう": 1171,
  "ごうちきゅうかんきょう": 2653,
  "いのちきょうせいども9": 1144,
  "いのちきょうどうたい」": 1736,
  "いのちきょうどうたいだ": 1457,
  "いのちきょうどうたいで": 3325,
  "いのちきょうどうたいと": 2964,
  "いのちきょうどうたいな": 1057,
  "いのちきょうどうたいに": 1131,
  "いのちきょうどうたいの": 3122,
  "いのちきゅうきゅうせん": 35943,
  "いのちきのうけんきゅう": 1279,
  "えんりょくちきょうかい": 2661,
  "ざいにちきたちょうせん": 2322,
  "ちきょういくけんきゅう": 2421,
  "ちきゅうのじゅうりょく": 1959,
  "ちきゅうじょうでおこし": 1622,
  "ちきゅうじょうにじゅう": 2167,
  "ちきゅうはくかいじょう": 1003,
  "ちきゅうもうじゅうぐん": 3086,
  "ちきゅうかんきょうもん": 12963,
  "ちきゅうかんきょうもと": 1004,
  "ちきゅうかんきょうへん": 3297,
  "ちきゅうかんきょうだい": 1830,
  "ちきゅうかんきょうがく": 6770,
  "ちきゅうかんきょうたい": 2553,
  "ちきゅうかんきょうせん": 1636,
  "ちきゅうかんきょううつ": 1093,
  "ちきゅうかんきょうとき": 2297,
  "ちきゅうかんきょうさん": 1557,
  "ちきゅうかんきょうけん": 7427,
  "ちきゅうかんきょうやぶ": 2495,
  "ちきゅうさんぎょうぶん": 3082,
  "ちきゅうかんそくまもる": 2717,
  "だいかいじゅうちきゅう": 1322,
  "たいようちきゅうたまき": 1699,
  "がくいんちきゅうたまき": 1168,
  "みのる(ちきゅうあつし": 4055,
  "しゃくはちきょうしつで": 4197,
  "やまいちきたごうちょう": 1347,
  "しゅういちきょういくい": 1256,
  "こうぎょうだんちきょう": 1340,
  "いちきしまひめのみこと": 3789,
  "へいせいいちきゅうねん": 1551,
  "とし(いちきゅうきゅう": 1894,
  "けいいちきろめーとるの": 1671,
  "けいいちきろめーとる以": 7757,
  "こうじーえいちきゅーに": 1190,
  "こうじーえいちきゅーの": 1604,
  "かいじゅうちきゅうさい": 1331,
  "せんごじーえいちきゅー": 1158,
  "にちきょうどう】ちゅう": 3002,
  "にちきょうどうつうしん": 1042,
  "にちきたちょうせんじん": 1156,
  "にちきょういくをくだり": 1270,
  "つきじゅういちにちきん": 1683,
  "つきじゅうさんにちきん": 1450,
  "つきじゅうろくにちきん": 2134,
  "つきじゅうはちにちきん": 1556,
  "つきにじゅうごにちきた": 1016,
  "つきにじゅうごにちきん": 1297,
  "つきさんじゅうにちきん": 1278,
  "ほんきょちきゅうじょう": 2744,
  "しょくみんちきょういく": 1396,
  "のこりいちきろめーとる": 1749,
  "すいけいいちきゅうかわ": 1231,
  "ほうじんちきゅうたまき": 1099,
  "げんざいちきゅうじょう": 1758,
  "かわらばんいちきさとる": 1106,
  "まちきゅうちょうめえき": 3460,
  "まちきぎょうしょくいん": 1005,
  "しゃ、いちきゅうきゅう": 1946,
  "わたしたちきょうしょく": 2029,
  "やくいちきろめーとる)": 5730,
  "やくいちきろめーとる、": 3190,
  "やくいちきろめーとるで": 1755,
  "やくいちきろめーとるに": 4631,
  "やくいちきろめーとるの": 17888,
  "やくいちきろめーとるほ": 1551,
  "やくはちきろめーとる、": 1296,
  "やくはちきろめーとるに": 1349,
  "やくはちきろめーとるの": 4805,
  "そうごうちきゅうたまき": 2630,
  "せんぱくちきゅうきょく": 1119,
  "かばのまちきたかつしか": 1072,
  "まちきょうどうくみあい": 3761,
  "さいちきたじょうちょう": 2177,
  "せっけいいちきゅうけん": 7118,
  "たにまちきゅうちょうめ": 2024,
  "みちをいちきろめーとる": 1249,
  "みちきぎょうしょくいん": 1041,
  "みちきたおおさかきゅう": 3541,
  "みちきょくしょくいんの": 1619,
  "みちきょうしつをひらき": 2356,
  "みちきょういくだいがく": 11917,
  "じゅういちきろぐらむあ": 2417,
  "じゅうがいちきろぐらむ": 1079,
  "りょう:いちきろぐらむ": 1213,
  "いんちきゅうかんきょう": 1800,
  "せいしゅんじゅうはちき": 1527,
  "(じゅうはちきん)にち": 1068,
  "(じーえいちきゅー)の": 1988,
  "(あいちきょういくだい": 1192,
  "じゅうににちきんようび": 1233,
  "じゅうごにちきんようび": 1001,
  "じゅうはちきん)であい": 9612,
  "じゅうくにちきんようび": 1418,
  "いちきゅうはちよん」の": 1016,
  "いちきろぐらむにたいし": 1190,
  "いちきろぐらむていどの": 1033,
  "いちきろめーとるあたり": 1844,
  "いちきろめーとるくらい": 5795,
  "いちきろめーとるぐらい": 2566,
  "いちきろめーとるちょっ": 1290,
  "いちきろめーとるにわた": 2878,
  "いちきろめーとるのとこ": 1485,
  "いちきろめーとるほどで": 1463,
  "いちきろめーとるほどふ": 1188,
  "いちきろめーとるおーば": 1749,
  "いちきろめーとるめっし": 1056,
  "いちきょくからかんたん": 10793,
  "さんじゅうせんちきゅう": 1647,
  "よんじゅうせんちきゅう": 1531,
  "はちきろめーとるくらい": 1370,
  "はちきろめーとるにわた": 1388,
  "よりはちきろめーとるC": 1259,
  "じーえいちきゅーによっ": 3053,
  "じーえいちきゅーにより": 2209,
  "じーえいちきゅーによる": 4919,
  "ちきゅうさいきょうのs": 1419,
  "ちきゅうさいきょうvs": 1417,
  "、じゅうはちきんなとう": 20067,
  "、いちきろめーとるほど": 1555,
  "、じーえいちきゅーによ": 2583,
  "、「ちきゅうかんきょう": 3771,
  "、いちきゅうななにねん": 1844,
  "、いちきゅうななごねん": 1578,
  "、いちきゅうにれいねん": 1332,
  "、いちきゅうごれいねん": 2416,
  "、いちきゅうごいちねん": 1135,
  "、いちきゅうはちにねん": 1625,
  "、いちきゅうはちごねん": 2207,
  "、いちきゅうろくにねん": 1282,
  "、いちきゅうろくごねん": 1566,
  "、いちきゅうよんごねん": 3086,
  "、いちきょしゅいっとう": 2230,
  "、いっちきょうりょくし": 1458,
  "、はんにちきょういくを": 1369,
  "、ちきゅうのちゅうしん": 1810,
  "、ちきゅうのいんりょく": 1097,
  "、ちきゅうのかんきょう": 4492,
  "、ちきゅうのひょうめん": 1868,
  "、ちきゅうじょうでさい": 2332,
  "、ちきゅうじょうにそん": 1333,
  "、ちきゅうじょうになま": 1083,
  "、ちきゅうじょうのぜん": 1812,
  "、ちきゅうがいせいめい": 2494,
  "、ちきゅうかんきょう、": 1955,
  "、ちきゅうかんきょうが": 1499,
  "、ちきゅうかんきょうと": 3837,
  "、ちきゅうかんきょうに": 19957,
  "、ちきゅうかんきょうの": 17496,
  "、ちきゅうかんきょうは": 1269,
  "、ちきゅうかんきょうへ": 4176,
  "、ちきゅうかんきょうや": 2049,
  "、ちきゅうかんきょうを": 10346,
  "、ちきゅうかんきょうほ": 9729,
  "、ちきゅうれんぽうせい": 1107,
  "、ちきゅうれんぽうぐん": 2591,
  "、ちきゅうぼうえいぐん": 3049,
  "、あいちきょういくだい": 1927,
  "、まちきょういくいいん": 1298,
  "、きんだいちきょうすけ": 1388,
  "「いちきゅうはちよん」": 5302,
  "「はんにちきょういく」": 1482,
  "「ちきゅうたんけんたい": 1121,
  "「ちきゅうかんきょう」": 2629,
  "「ちきゅうかんきょうと": 2582,
  "「ちきゅうかんきょうに": 2299,
  "「ちきゅうかんきょうの": 2419,
  "「ちきゅうかんきょうを": 2021,
  "「ちきゅうかんきょうほ": 1927,
  "「ちきゅうぼうえいぐん": 2065,
  "「うちゅうせんちきゅう": 1923,
  "」「ちきゅうかんきょう": 1038,
  "『いちきゅうはちよん』": 4850,
  "あるちきゅうかんきょう": 1579,
  "い、ちきゅうかんきょう": 1524,
  "いるちきゅうかんきょう": 1808,
  "いちきゅうかんきょうの": 1204,
  "いちきゅうかんきょうを": 2139,
  "いあだちきよしいりょう": 3688,
  "え、ちきゅうかんきょう": 1003,
  "えるちきゅうかんきょう": 1215,
  "およそいちきろめーとる": 1261,
  "からいちきろめーとるほ": 3029,
  "からいちきろめーとる以": 2522,
  "からちきゅうかんきょう": 6212,
  "が、ちきゅうかんきょう": 4107,
  "がいっちきょうりょくし": 3672,
  "がちきゅうにしょうとつ": 3154,
  "がちきゅうかんきょうに": 3064,
  "がちきゅうかんきょうの": 1463,
  "がちきゅうかんきょうを": 1727,
  "く、ちきゅうかんきょう": 2098,
  "ぐちきょういくおうえん": 1171,
  "けるちきゅうかんきょう": 1807,
  "こからいちきろめーとる": 1087,
  "このちきゅうかんきょう": 1211,
  "し、ちきゅうかんきょう": 7717,
  "しいちきゅうかんきょう": 1360,
  "したちきゅうかんきょう": 2105,
  "して、いちきゅうきゅう": 1356,
  "してはんにちきょういく": 1513,
  "してちきゅうかんきょう": 5471,
  "じてちきゅうかんきょう": 1174,
  "するちきゅうかんきょう": 2866,
  "た、ちきゅうかんきょう": 2573,
  "たのはいちきゅうきゅう": 1575,
  "たちきゅうかんきょうに": 1225,
  "たちきゅうかんきょうの": 1135,
  "ってちきゅうかんきょう": 1546,
  "ていちきろめーとるほど": 1004,
  "て、ちきゅうかんきょう": 7279,
  "てはんにちきょういくを": 1578,
  "てちきゅうかんきょうに": 2226,
  "てちきゅうかんきょうの": 1872,
  "てちきゅうかんきょうを": 1535,
  "で、ちきゅうかんきょう": 4630,
  "ではちきゅうかんきょう": 2019,
  "でちきゅうかんきょうに": 2804,
  "でちきゅうかんきょうの": 1062,
  "でちきゅうかんきょうを": 1773,
  "と、ちきゅうかんきょう": 1898,
  "とちきゅうかんきょうに": 2758,
  "とちきゅうかんきょうの": 3878,
  "とちきゅうかんきょうを": 2220,
  "とちきゅうかんきょうほ": 1447,
  "ど、ちきゅうかんきょう": 2168,
  "どのちきゅうかんきょう": 1330,
  "ないちきゅうかんきょう": 2017,
  "などちきゅうかんきょう": 2247,
  "なちきゅうかんきょうの": 1204,
  "なちきゅうかんきょうを": 1592,
  "なうちゅうせんちきゅう": 6167,
  "にいちきろめーとるほど": 1776,
  "に、ちきゅうかんきょう": 5205,
  "にはちきゅうかんきょう": 1428,
  "にもちきゅうかんきょう": 1132,
  "にちきゅうかんきょうに": 2041,
  "にちきゅうかんきょうの": 1315,
  "にちきゅうかんきょうを": 1573,
  "の「いちきゅうはちよん": 1028,
  "の「ちきゅうかんきょう": 1041,
  "のは、いちきゅうきゅう": 1392,
  "のいちきょしゅいっとう": 14932,
  "のいちきゅうじっこんに": 1230,
  "のちきゅうじょうにそん": 1231,
  "のちきゅうじょうになま": 1179,
  "のちきゅうがいせいめい": 1407,
  "のちきゅうかんきょうに": 2146,
  "のちきゅうかんきょうの": 2191,
  "のちきゅうかんきょうを": 3031,
  "のちきゅうかんきょうほ": 1549,
  "のちきゅうぼうえいぐん": 1175,
  "のしきちきょうかいせん": 1080,
  "のまどぐちきょうとてん": 1314,
  "はじーえいちきゅーによ": 1197,
  "は、じーえいちきゅーの": 1719,
  "は、いちきゅうきゅうご": 1264,
  "は、ちきゅうかんきょう": 16340,
  "は「ちきゅうかんきょう": 2321,
  "はいちきゅうごれいねん": 1032,
  "はいちきゅうよんごねん": 1252,
  "はちきゅうのかんきょう": 1019,
  "はちきゅうじょうでさい": 1569,
  "はちきゅうじょうにそん": 1066,
  "はちきゅうがいせいめい": 1160,
  "はちきゅうかんきょうに": 4490,
  "はちきゅうかんきょうの": 3104,
  "はちきゅうかんきょうを": 3108,
  "はちきゅうかんきょうほ": 1646,
  "はちきゅうぼうえいぐん": 1282,
  "ば、ちきゅうかんきょう": 1100,
  "またちきゅうかんきょう": 1018,
  "め、ちきゅうかんきょう": 1729,
  "も、ちきゅうかんきょう": 2097,
  "もちきゅうかんきょうに": 1977,
  "や、ちきゅうかんきょう": 1023,
  "やちきゅうかんきょうに": 1971,
  "やちきゅうかんきょうの": 1749,
  "よりちきゅうかんきょう": 1291,
  "よるちきゅうかんきょう": 2725,
  "ら、ちきゅうかんきょう": 2434,
  "らのちきゅうかんきょう": 1336,
  "らちきゅうかんきょうを": 2055,
  "り、ちきゅうかんきょう": 5395,
  "る「ちきゅうかんきょう": 1001,
  "るちきゅうかんきょうに": 1014,
  "るちきゅうかんきょうの": 2442,
  "るちきゅうかんきょうほ": 1726,
  "れ、ちきゅうかんきょう": 1078,
  "をいちきろめーとるほど": 1298,
  "をちゅうしんにちきゅう": 1118,
  "のいちきゅうじっこんや": 1131,
  "らすといちきろめーとる": 1405,
  "じょうほう-ちきゅうる": 1396,
  "・いちきろめーとるおー": 1548,
  "・ちきゅうはくぶつかん": 2834,
  "・ちきゅうわくせいけん": 1136,
  "・ちきゅうかんきょうに": 1681,
  "・ちきゅうかんきょうは": 1262,
  "とちきゅうかんきょうー": 1120,
  "いちきゅうななにねんに": 1237,
  "いちきゅうななにねんの": 1254,
  "いちきゅうななごねんに": 1044,
  "いちきゅうはちにねんに": 1065,
  "いちきゅうはちごねんに": 1502,
  "いちきゅうはちごねんの": 1035,
  "いちきゅうよんごねんの": 1642,
  "いちきょうかい、ほうの": 1407,
  "いちきょうかいへのつう": 2478,
  "いちきゅうじっこんによ": 1232,
  "いっちきょうりょくして": 7592,
  "いちきねんびじゅつかん": 1194,
  "せいきのちきゅうたまき": 1113,
  "なかいちきょうどのもり": 4795,
  "なかまちきかくじゅよう": 2143,
  "ひとのいのちはちきゅう": 1977,
  "じんいんはいちきじゅん": 1630,
  "いま、ちきゅうおんだん": 1014,
  "じゅうみんじちきょうぎ": 3357,
  "ほしょうそちきょうてい": 2118,
  "くらあきらの「ちきゅう": 1009,
  "へんさちきょうだいせき": 11808,
  "おくねんまえにちきゅう": 1026,
  "おくねんまえのちきゅう": 1176,
  "うちきぎょうのどうこう": 1088,
  "うちきぎょうぶっかゆび": 1078,
  "うちきぎょうかんれんに": 4547,
  "うちきょじゅうしゃのみ": 6615,
  "うちきしょうのせいどう": 3480,
  "うちきんえんをすいしん": 1521,
  "か、ちきゅうかんきょう": 1586,
  "くじゅうみんじちきょう": 1015,
  "ひろし(あい・ちきゅう": 1837,
  "およびちきゅうおんだん": 1270,
  "はんにちきょういくして": 1351,
  "はんにちきょういくをし": 1643,
  "はんにちきょういくを受": 3249,
  "いのちのほし・ちきゅう": 6496,
  "いのちきょうさいなら、": 3179,
  "いのちきょうさいは、か": 3135,
  "ぜんの『ちきゅうあつし": 1458,
  "くにのちきゅうおんだん": 1073,
  "くにちきゅうおんだんか": 1474,
  "ちきょくちかくにじゅう": 1560,
  "ちきゅうがたんじょうし": 1241,
  "ちきゅうにだいせっきん": 1103,
  "ちきゅうにさいせっきん": 1536,
  "ちきゅうにしょうとつし": 2237,
  "ちきゅうにしょうとつす": 3161,
  "ちきゅうのちゅうしんに": 1982,
  "ちきゅうのはんたいがわ": 2158,
  "ちきゅうのいんりょくに": 1657,
  "ちきゅうのかんきょうが": 1147,
  "ちきゅうのかんきょうに": 2184,
  "ちきゅうのかんきょうは": 1085,
  "ちきゅうのかんきょうを": 4479,
  "ちきゅうのかんきょうほ": 1366,
  "ちきゅうのせいたいけい": 2644,
  "ちきゅうのしぜんたまき": 1200,
  "ちきゅうのひょうめんに": 1300,
  "ちきゅうのひょうめんを": 1185,
  "ちきゅうをいっしゅうし": 2043,
  "ちきゅうをいっしゅうす": 1443,
  "ちきゅうをちゅうしんに": 1005,
  "ちきゅうをしんりゃくし": 1486,
  "ちきゅうをしんりゃくす": 1011,
  "ちきゅうじょうのすべて": 5332,
  "ちきゅうしんりゃくを企": 1027,
  "ちきゅうかがくてきけん": 1600,
  "ちきゅうがいちてきせい": 3068,
  "ちきゅうしょうじょある": 1024,
  "ちきゅうわくせいかがく": 8651,
  "ちきゅうたんけんたい」": 1081,
  "ちきゅうさいだいのけつ": 1932,
  "ちきゅうさいだいのにく": 2075,
  "ちきゅうさいきょうのや": 1434,
  "ちきゅうさいごのおとこ": 1754,
  "ちきゅうおんだんかはら": 1086,
  "ちきゅうおんだんかもん": 8687,
  "ちきゅうおんだんかたい": 23117,
  "ちきゅうおんだんけげん": 3036,
  "ちきゅうおんだんかとう": 2133,
  "ちきゅうおんだんかせつ": 1641,
  "ちきゅうおんだんかろん": 2612,
  "ちきゅうおんだんかぼう": 26425,
  "ちきゅうぶつりがくてき": 1640,
  "ちきゅうぶつりがくしゃ": 2532,
  "ちきゅうかんきょうとい": 1300,
  "ちきゅうかんきょうとの": 3517,
  "ちきゅうかんきょうとえ": 1464,
  "ちきゅうかんきょうなど": 1196,
  "ちきゅうかんきょうにつ": 4733,
  "ちきゅうかんきょうにと": 1536,
  "ちきゅうかんきょうにも": 1208,
  "ちきゅうかんきょうにや": 3810,
  "ちきゅうかんきょうにふ": 1455,
  "ちきゅうかんきょうのこ": 2801,
  "ちきゅうかんきょうのた": 1828,
  "ちきゅうかんきょうのほ": 2707,
  "ちきゅうかんきょうの危": 1661,
  "ちきゅうかんきょうのみ": 1065,
  "ちきゅうかんきょうはど": 2149,
  "ちきゅうかんきょうへの": 2677,
  "ちきゅうかんきょうまで": 1102,
  "ちきゅうかんきょうをほ": 1600,
  "ちきゅうかんきょうさみ": 1179,
  "ちきゅうかんきょうぱー": 1293,
  "ちきゅうかんきょう・え": 1462,
  "ちきゅうかんきょうほご": 2335,
  "ちきゅうかんきょうこど": 1026,
  "ちきゅうかんきょうふか": 1271,
  "ちきゅうはかいばくだん": 1652,
  "ちきゅうかがくいっぱん": 6911,
  "ちきゅうたんじょうから": 1422,
  "ちきゅうれんごうぐんの": 1432,
  "ちきゅうれんぽうせいふ": 4122,
  "ちきゅうれんぽうぐんに": 1069,
  "ちきゅうれんぽうぐんの": 1016,
  "ちきゅうぼうえいぐん2": 1221,
  "ちきゅうぼうえいぐん」": 1710,
  "ちきゅうぼうえいぐんの": 1206,
  "ちきゅうぼうえいぐんは": 1201,
  "ちきゅうぼうえいぐんを": 1060,
  "ほうまんさいのちきゅう": 1931,
  "そとりょこうのちきゅう": 1005,
  "だいがくせっちきじゅん": 5326,
  "まなぶ・ちきゅうかがく": 1120,
  "がっこうせっちきじゅん": 1303,
  "がくいんせっちきじゅん": 2051,
  "うちゅうじんがちきゅう": 2906,
  "うちゅうじんはちきゅう": 1791,
  "そらふねちきゅうごう」": 3530,
  "そらふねちきゅうごうの": 1994,
  "みやいちきそがわちょう": 5341,
  "こぐちきょくしょうしみ": 1757,
  "おいちきょういくいいん": 1001,
  "たむろちきねんぎょうじ": 1072,
  "やまいちきたくはなじり": 2154,
  "やまだたいちきゃくほん": 1072,
  "やまりゅういちきねんま": 1407,
  "おかいちきんこうのほう": 2223,
  "かわいちきしがわちょう": 7961,
  "さちきょうだいかんけい": 11808,
  "しよしままちきたよしみ": 1636,
  "とし、ちきゅうおんだん": 2224,
  "としのちきゅうおんだん": 1490,
  "ねんどちきゅうおんだん": 1097,
  "しきかいしゃちきゅうの": 1441,
  "ひろしの『ちきゅうむら": 1204,
  "とうがいたちきのところ": 2363,
  "ご、じーえいちきゅーの": 1242,
  "せいとちきゅうおんだん": 1537,
  "せいむけじゅうはちきん": 1136,
  "つねの『ちきゅうあつし": 2482,
  "じょうほう-ちきゅうの": 3511,
  "じょうほう|ちきゅうの": 1091,
  "じょうほうつうちきのう": 1935,
  "あいはちきゅうをすくい": 1985,
  "あいちきかいこうぎょう": 1225,
  "といちきょういくいいん": 3570,
  "とまちきたかつしかぐん": 4285,
  "うちきあかがわあまぐり": 1001,
  "しきちきょうかいせんか": 1228,
  "にち、ちきゅうおんだん": 2895,
  "にちきんろうかんしゃの": 1527,
  "にちきしゃはっぴょうし": 1593,
  "めいの「ちきゅうじゅく": 1009,
  "ほし・ちきゅうはくぶつ": 6022,
  "えいが「ちきゅうよしみ": 1126,
  "しょせきめい:ちきゅう": 2204,
  "つきじゅうくにちきょう": 1044,
  "つきよりちきゅうあつし": 2476,
  "もちきんがくまんえん(": 3178,
  "ほんちきゅうわくせいか": 1650,
  "すぎとまちきたかつしか": 4285,
  "きのちきゅうかんきょう": 1438,
  "らいにちきしゃかいけん": 1276,
  "いた(じゅうはちきん)": 1092,
  "ちきょうしょうかいぎの": 1421,
  "ちきょくじょうむいいん": 6580,
  "しぶさわえいいちきねん": 2050,
  "ちちきししんすけがぶん": 1163,
  "うしいちきろぐらむを2": 1311,
  "とくにちきゅうおんだん": 1050,
  "ししちきゅうさいだいの": 1326,
  "たまぐんきさいまちきた": 1813,
  "せいぶつちきゅうかがく": 1384,
  "たいちきょういくいいん": 7018,
  "たまちきょういくいいん": 1359,
  "まちきかくじゅようぶん": 2143,
  "まちきたさいたまぐんき": 2015,
  "まちきそくだいいちごう": 1309,
  "まちきそくだいさんごう": 1028,
  "まちきそくだいよんごう": 1046,
  "まちきんりん-きょうと": 1376,
  "が「ちきゅうこうきょう": 1129,
  "てきなちきゅうおんだん": 1913,
  "けんちきゅうおんだんか": 7795,
  "ちきょういくだいがくの": 1456,
  "ちきょういくだいがくふ": 1060,
  "ふくながゆういちきしゅ": 1502,
  "こう、じゅうはちきんな": 20067,
  "たちきのところまします": 2369,
  "おきじょうほうつうちき": 1864,
  "のうなちきゅうしゃかい": 1004,
  "おちきょうどうたいのじ": 1488,
  "そばむぎうちきょうしつ": 1167,
  "にしまちよしみまちきち": 1044,
  "はなしのきちきょくこん": 1558,
  "にんちきのうしょうがい": 3501,
  "かたりじてんへんいちき": 1109,
  "みちきょうかいせんから": 1069,
  "くるまとうほうちきんし": 1064,
  "てんしゃとうほうちきん": 1064,
  "つうじてちきゅうたまき": 1148,
  "みちきゅうごうせんから": 1344,
  "みちきゅうごうせんぞい": 3058,
  "みちきたひろしましにし": 2061,
  "みちきょくしていこうじ": 1675,
  "みちきかんへのおおやけ": 1046,
  "みちきょうどりょうりを": 1782,
  "ぐんきたかわべまちきた": 1729,
  "ぐんきさいまちきたさき": 1750,
  "ぶ(じーえいちきゅー)": 4861,
  "のいちきたのみねちょう": 2191,
  "のいちきっしょうてらの": 1638,
  "のいちきょういくいいん": 5530,
  "のまちきょういくいいん": 1180,
  "きんやじゅうはちきん、": 39985,
  "きむ・じゅうはちきんぷ": 25248,
  "きんだいちきょうすけの": 1316,
  "ちょうかたみちきっぷの": 3389,
  "いんせっちきじゅんだい": 1108,
  "りんちきょうかいせんか": 1178,
  "りんちきょうかいせんま": 1219,
  "だい(ちきゅうおんだん": 1076,
  "だい、ちきゅうおんだん": 1185,
  "だいとちきゅうおんだん": 1824,
  "えきまるのうちきたぐち": 3560,
  "ちゅうとんちきねんゆき": 1070,
  "きさいまちきたさいたま": 1750,
  "(じゅうはちきん)から": 1052,
  "(ぜんちきゅうそくいし": 2105,
  "(ちきゅうのあるきかた": 2631,
  "(ちきゅうおんだんか)": 1308,
  "(ちきゅうおんだんかと": 2980,
  "(ちきゅうおんだんかの": 2916,
  "-ちきゅうのあるきかた": 19094,
  "/ちきゅうのあるきかた": 1080,
  ")ちきゅうおんだんか1": 1440,
  "じゅうはちきっぷのたび": 9057,
  "じゅうはちきっぷりよう": 1373,
  "じゅうはちきん)からあ": 1046,
  "じゅうはちきんじゃない": 1805,
  "じゅうはちきん、ぷらち": 40114,
  "じゅうはちきんぷらちな": 25307,
  "いちきろぐらむあたり1": 1100,
  "いちきろぐらむやせただ": 2034,
  "ななねんぶりにちきゅう": 1285,
  ":「ちきゅうおんだんか": 1012,
  ":ちきゅうのあるきかた": 1841,
  ":ちきゅうおんだんかを": 1056,
  "しーえーちきゅうひろば": 1655,
  "はまぐちきょうこあにE": 2796,
  "じーえいちきゅー/すか": 1226,
  "あいえいちきっちんけん": 2914,
  "(ぜんちきゅうそくいS": 2091,
  "きちきょくからはなれT": 1613,
  "はまぐちきょうこYLE": 2796,
  "ちきゅうあつしfrom": 1144,
  "おむちきゅうおんだんか": 1150,
  "ちきゅうおんだんrom": 1144,
  "いちきゅううんちくしy": 1373,
  "|ちきゅうのあるきかた": 8538,
  "、「ちきゅうおんだんか": 7514,
  "、このちきゅうじょうで": 2284,
  "、このちきゅうじょうに": 3362,
  "、そしてちきゅうたまき": 1069,
  "、ちきゅうがたいようの": 1059,
  "、ちきゅうのへいきんき": 1332,
  "、ちきゅうのあるきかた": 3835,
  "、ちきゅうのおんだんか": 5517,
  "、ちきゅうのうらがわで": 1267,
  "、ちきゅうのうらがわの": 1004,
  "、ちきゅうじょうのあら": 2089,
  "、ちきゅうじょうのすべ": 1599,
  "、ちきゅうじょうのどこ": 1293,
  "、ちきゅうおんだんか、": 4408,
  "、ちきゅうおんだんかが": 1028,
  "、ちきゅうおんだんかで": 2391,
  "、ちきゅうおんだんかと": 4131,
  "、ちきゅうおんだんかな": 3724,
  "、ちきゅうおんだんかに": 13891,
  "、ちきゅうおんだんかの": 31070,
  "、ちきゅうおんだんかは": 2790,
  "、ちきゅうおんだんかへ": 1438,
  "、ちきゅうおんだんかや": 4391,
  "、ちきゅうおんだんかを": 9161,
  "、ちきゅうきぼのたまき": 2374,
  "、うちゅうからちきゅう": 1206,
  "、うつくしいちきゅうを": 1081,
  "、じちきほんじょうれい": 4284,
  "「ちきゅうのあるきかた": 40549,
  "「ちきゅうおんだんか」": 11209,
  "「ちきゅうおんだんかと": 3050,
  "「ちきゅうおんだんかに": 3646,
  "「ちきゅうおんだんかの": 5783,
  "「ちきゅうおんだんかは": 1388,
  "「ちきゅうおんだんかを": 1960,
  "「じちきほんじょうれい": 2666,
  "」「ちきゅうおんだんか": 1209,
  "」は、ちきゅうおんだん": 1570,
  "『ちきゅうのあるきかた": 5482,
  "『ちきゅうむらのじけん": 1349,
  "『ちきゅうおんだんかの": 1818,
  "『ちきゅうおんだんかび": 3856,
  "【ちきゅうのあるきかた": 1644,
  "】まちきんゆうのせかい": 1084,
  "あり、ちきゅうおんだん": 1488,
  "あるちきゅうおんだんか": 1653,
  "い、ちきゅうおんだんか": 1213,
  "いて、ちきゅうおんだん": 1218,
  "いるちきゅうおんだんか": 4625,
  "いがくふをいちきょくか": 10795,
  "う、ちきゅうおんだんか": 160462,
  "う・こうかんちきゅうに": 2352,
  "え、ちきゅうおんだんか": 1511,
  "おけるちきゅうおんだん": 3970,
  "おり、ちきゅうおんだん": 1448,
  "か、ちきゅうおんだんか": 1454,
  "から、ちきゅうおんだん": 2284,
  "からちきゅうおんだんか": 4648,
  "が、ちきゅうおんだんか": 9548,
  "が「ちきゅうおんだんか": 1376,
  "がこのちきゅうじょうに": 1214,
  "がいちきんゆうきかんが": 1125,
  "がちきゅうおんだんかに": 2583,
  "がちきゅうおんだんかの": 4050,
  "がちきゅうおんだんかを": 2118,
  "き、ちきゅうおんだんか": 1264,
  "きるちきゅうおんだんか": 1933,
  "く、ちきゅうおんだんか": 2155,
  "くちきゅうのたまものは": 1224,
  "けるちきゅうおんだんか": 4141,
  "けんのまどぐちきょうと": 1320,
  "ことで、ちきゅうあつし": 1212,
  "このちきゅうじょうから": 2141,
  "このちきゅうじょうには": 2056,
  "このちきゅうおんだんか": 1633,
  "このうつくしいちきゅう": 1449,
  "これもちきゅうおんだん": 3513,
  "され、ちきゅうおんだん": 1006,
  "し、ちきゅうおんだんか": 10248,
  "しいがくふをいちきょく": 10813,
  "したちきゅうおんだんか": 3191,
  "して、ちきゅうおんだん": 4353,
  "してちきゅうおんだんか": 5313,
  "すが、ちきゅうおんだん": 2220,
  "するちきゅうおんだんか": 4778,
  "ず、ちきゅうおんだんか": 1054,
  "た、ちきゅうおんだんか": 3615,
  "た「ちきゅうおんだんか": 1904,
  "たっぷりいちきろぐらむ": 3795,
  "ため、ちきゅうおんだん": 1742,
  "たちきゅうおんだんかの": 1623,
  "ちきんぞくかこうきかい": 1071,
  "ったちきゅうおんだんか": 1579,
  "って、ちきゅうおんだん": 1598,
  "っているちきゅうあつし": 2013,
  "ってちきゅうおんだんか": 2287,
  "て、ちきゅうおんだんか": 9431,
  "て「ちきゅうおんだんか": 1043,
  "ているちきゅうおんだん": 4410,
  "ており、ちきゅうあつし": 1210,
  "ては、ちきゅうおんだん": 1488,
  "てちきゅうおんだんかの": 1780,
  "てちきゅうおんだんかを": 1343,
  "で、ちきゅうおんだんか": 7885,
  "で「ちきゅうおんだんか": 1018,
  "であるちきゅうおんだん": 1053,
  "できるちきゅうおんだん": 1921,
  "ですが、ちきゅうあつし": 1109,
  "でのちきゅうおんだんか": 1511,
  "では、ちきゅうおんだん": 6442,
  "ではちきゅうおんだんか": 3223,
  "でもちきゅうおんだんか": 1818,
  "でちきゅうのかげにいり": 1882,
  "でちきゅうおんだんかに": 1519,
  "でちきゅうおんだんかの": 3494,
  "でちきゅうおんだんかを": 1483,
  "と、ちきゅうおんだんか": 3575,
  "として、ちきゅうあつし": 1676,
  "として、ちきゅうたまき": 1475,
  "としてちきゅうおんだん": 1522,
  "とで、ちきゅうおんだん": 1229,
  "とは、ちきゅうおんだん": 1210,
  "ともに、ちきゅうあつし": 1171,
  "ともに、ちきゅうたまき": 1168,
  "とちきゅうのかいてん」": 2119,
  "とちきゅうのかいてん』": 2063,
  "とちきゅうおんだんかに": 1101,
  "とちきゅうおんだんかの": 2065,
  "ど、ちきゅうおんだんか": 1979,
  "なく、ちきゅうおんだん": 1296,
  "など、ちきゅうおんだん": 1513,
  "などちきゅうおんだんか": 1374,
  "に、ちきゅうおんだんか": 7545,
  "に「ちきゅうおんだんか": 1630,
  "におけるちきゅうあつし": 3969,
  "におけるちきゅうたまき": 1723,
  "には、ちきゅうおんだん": 1541,
  "にはちきゅうおんだんか": 1861,
  "により、ちきゅうあつし": 1484,
  "により、ちきゅうたまき": 1108,
  "によるちきゅうおんだん": 8820,
  "にちきゅうおんだんかに": 1277,
  "にちきゅうおんだんかの": 2773,
  "の「ちきゅうおんだんか": 2389,
  "の『ちきゅうむらのこと": 1196,
  "の『ちきゅうおんだんか": 7329,
  "のいのちはちきゅうより": 2321,
  "のざいにちきしゃ「ぼく": 1381,
  "のちきゅうのあるきかた": 4902,
  "のちきゅうおんだんかに": 1876,
  "のちきゅうおんだんかの": 5050,
  "のきちきょくめんきょと": 1907,
  "のしんしょうひん「ちき": 2305,
  "のじちきほんじょうれい": 1878,
  "のわ[じゅうはちきん]": 1084,
  "はろくがつよりちきゅう": 2456,
  "は、「ちきゅうおんだん": 1858,
  "は、このちきゅうじょう": 1757,
  "は、ちきゅうおんだんか": 38761,
  "は、まちきそくでじょう": 1201,
  "は「ちきゅうおんだんか": 4526,
  "はりちきゅうおんだんか": 1142,
  "はざいにちきぎょうえす": 1154,
  "はちきゅうのあるきかた": 1064,
  "はちきゅうのおんだんか": 1035,
  "はちきゅうおんだんかが": 1188,
  "はちきゅうおんだんかと": 1088,
  "はちきゅうおんだんかに": 2986,
  "はちきゅうおんだんかの": 6920,
  "はちきゅうおんだんかを": 2610,
  "はやまぐちきょうくつの": 1531,
  "ば、ちきゅうおんだんか": 2124,
  "ほけんのまどぐちきょう": 1320,
  "ぼくがちきゅうをすくい": 1191,
  "ますが、ちきゅうあつし": 1106,
  "また、ちきゅうおんだん": 3036,
  "またちきゅうおんだんか": 1134,
  "みのいちきたあだちぐん": 3663,
  "め、ちきゅうおんだんか": 2524,
  "めよう、ちきゅうあつし": 160105,
  "も、ちきゅうおんだんか": 3948,
  "もに、ちきゅうおんだん": 1172,
  "もちきゅうおんだんかの": 4575,
  "やじゅうはちきん、ぷら": 39986,
  "や、ちきゅうおんだんか": 1591,
  "やはりちきゅうおんだん": 1141,
  "やちきゅうおんだんかな": 1123,
  "やちきゅうおんだんかに": 1137,
  "やちきゅうおんだんかの": 2034,
  "よう、ちきゅうおんだん": 160191,
  "より、ちきゅうおんだん": 1805,
  "よりちきゅうおんだんか": 3862,
  "よるちきゅうおんだんか": 8904,
  "ら、ちきゅうおんだんか": 3423,
  "らちきゅうおんだんかを": 1169,
  "り、ちきゅうおんだんか": 8446,
  "りちきゅうおんだんかの": 1237,
  "る「ちきゅうおんだんか": 2635,
  "ると、ちきゅうおんだん": 1365,
  "るちきゅうおんだんかに": 1526,
  "るちきゅうおんだんかの": 4802,
  "るじちきほんじょうれい": 1105,
  "れ、ちきゅうおんだんか": 1862,
  "れたちきゅうおんだんか": 1692,
  "れているちきゅうあつし": 1008,
  "れはちきゅうおんだんか": 1223,
  "れば、ちきゅうおんだん": 1152,
  "れもちきゅうおんだんか": 3639,
  "れるちきゅうおんだんか": 1561,
  "にかがやくちきゅうのあ": 1230,
  "おれがちきゅうをすくい": 1832,
  "「ひたちきょうせいはく": 4287,
  "くっきーいちきろぐらむ": 1199,
  "ちきゅうさいだいのぐす": 2029,
  "」こうひょうはつこちき": 2316,
  "さくやのいちきゅういり": 1131,
  "とうつくしいちきゅうす": 2493,
  "はやまぐちきょうくとた": 1531,
  "ちきんなんばんべんとう": 1620,
  "「ひたちきょうせいっく": 4287,
  "ちきゅうさいだいっぐす": 2029,
  "でーたはやまぐちきょう": 1531,
  "ちきゅうのもゆるとろぼ": 1054,
  "は、ちきゅうおんだんぷ": 6855,
  "みうごきが「ちきゅうの": 2339,
  "にかがやくちきゅうゅあ": 1230,
  "らすのちきゅうをすくい": 1759,
  "りさーちきぎょうじょう": 14560,
  "れあでちきゅうかいめつ": 1247,
  "いちきゅうけんんにんぐ": 1710,
  "・じゅうはちきんぷらち": 25251,
  "・こうかんちきゅうにや": 2352,
  "・ちきゅうはく(あいち": 2229,
  "・ちきゅうおんだんかの": 1113,
  "・ちきゅうおんだんかは": 1372,
  "はやまぐちきょうくーた": 1531,
  "は、ちきゅうあつしーぷ": 6830,
  "いちきょうかいですごし": 1239,
  "いっぽうてきにうちきり": 1487,
  "いちきんゆうきかんこー": 1394,
  "まるのうちきたぐちより": 1119,
  "こうかんちきゅうにやさ": 2352,
  "ひととちきゅうにやさし": 4485,
  "じんめいはちきゅうより": 1646,
  "にんげんのにんちきこう": 1148,
  "けん^たちきのばっさい": 1507,
  "いちじょうほうつうちき": 1864,
  "とものみらいとちきゅう": 8724,
  "かちきょうそう」でかち": 1526,
  "ぼくのちきゅうをまもっ": 1364,
  "ぜんじゅうたくのうちき": 2484,
  "ぜんちきゅうそくいしす": 5012,
  "ぜんめんたいけつ、ちき": 1509,
  "うちきょうつうなびげー": 1124,
  "うちきょうつうめにゅー": 27923,
  "うちきぼうび、しつもん": 23123,
  "かとうちゅう・ちきゅう": 5149,
  "きたまちきいながしまく": 1920,
  "はんにちきんむじかんの": 1267,
  "いのちはちきゅうよりも": 1150,
  "いのちきずをあたえられ": 1248,
  "きいちきたもとしやしお": 4410,
  "とちきょうかいせんなら": 1800,
  "ざいにちきぎょうえすえ": 1159,
  "ちきゅうがおんだんかし": 1820,
  "ちきゅうがめつぼうする": 2272,
  "ちきゅうというわくせい": 2113,
  "ちきゅうにやさしいなま": 1499,
  "ちきゅうにそんざいする": 1856,
  "ちきゅうにせっきんして": 1093,
  "ちきゅうにせっきんする": 1729,
  "ちきゅうのききをすくい": 1480,
  "ちきゅうのまわりをかい": 2836,
  "ちきゅうのへいわをもり": 3560,
  "ちきゅうのかげにはいり": 2241,
  "ちきゅうのみらいをいち": 160047,
  "ちきゅうのみらいをこう": 2069,
  "ちきゅうのあるきかたL": 2536,
  "ちきゅうのあるきかたT": 2049,
  "ちきゅうのあるきかたW": 1698,
  "ちきゅうのあるきかた[": 17504,
  "ちきゅうのあるきかた「": 3445,
  "ちきゅうのあるきかた」": 33306,
  "ちきゅうのあるきかた』": 4123,
  "ちきゅうのあるきかた】": 1039,
  "ちきゅうのあるきかたが": 2479,
  "ちきゅうのあるきかたに": 3812,
  "ちきゅうのあるきかたの": 2298,
  "ちきゅうのあるきかたを": 1783,
  "ちきゅうのあるきかたえ": 1420,
  "ちきゅうのあるきかたか": 1053,
  "ちきゅうのあるきかたさ": 2292,
  "ちきゅうのあるきかたす": 5904,
  "ちきゅうのあるきほうと": 33604,
  "ちきゅうのあるきかたほ": 5992,
  "ちきゅうのあるきかたり": 1998,
  "ちきゅうのあるきかた・": 1154,
  "ちきゅうのれきしのなか": 1263,
  "ちきゅうのおんだんか、": 1058,
  "ちきゅうのおんだんかが": 2990,
  "ちきゅうのおんだんかと": 1146,
  "ちきゅうのおんだんかに": 2317,
  "ちきゅうのおんだんかの": 1400,
  "ちきゅうのおんだんかは": 1593,
  "ちきゅうのおんだんかを": 2691,
  "ちきゅうのじてんそくど": 1553,
  "ちきゅうのうらがわから": 2890,
  "ちきゅうのうらがわまで": 2781,
  "ちきゅうのたまものは、": 1224,
  "ちきゅうはおんだんかし": 1262,
  "ちきゅうをたいせつにし": 1104,
  "ちきゅうじょうからきえ": 1929,
  "ちきゅうじょうでもっと": 2216,
  "ちきゅうじょうにおいて": 1132,
  "ちきゅうじょうにおける": 1606,
  "ちきゅうじょうのあらゆ": 5959,
  "ちきゅうじょうのどこか": 1859,
  "ちきゅうじょうのどこに": 1673,
  "ちきゅうじょうのほとん": 1031,
  "ちきゅうせんたいふぁい": 1118,
  "ちきゅうむらのじけんぼ": 1478,
  "ちきゅうろまんきこう☆": 1126,
  "ちきゅうおんだんか」と": 1684,
  "ちきゅうおんだんか」に": 1260,
  "ちきゅうおんだんか」の": 1928,
  "ちきゅうおんだんか」を": 1712,
  "ちきゅうおんだんかって": 2119,
  "ちきゅうおんだんかとい": 4682,
  "ちきゅうおんだんかとか": 1300,
  "ちきゅうおんだんかとの": 1125,
  "ちきゅうおんだんかとは": 2788,
  "ちきゅうおんだんかなど": 9068,
  "ちきゅうおんだんかなん": 1033,
  "ちきゅうおんだんかにC": 2040,
  "ちきゅうおんだんかにつ": 9473,
  "ちきゅうおんだんかにも": 1020,
  "ちきゅうおんだんかによ": 18332,
  "ちきゅうおんだんかのせ": 3636,
  "ちきゅうおんだんかのた": 1514,
  "ちきゅうおんだんかのめ": 1205,
  "ちきゅうおんだんかの危": 2049,
  "ちきゅうおんだんかは、": 2993,
  "ちきゅうおんだんかへの": 6793,
  "ちきゅうおんだんかをは": 1670,
  "ちきゅうおんだんかを促": 1028,
  "ちきゅうおんだんかがす": 4491,
  "ちきゅうおんだんかさぎ": 1124,
  "ちきゅうりょくかせんた": 1706,
  "ちきゅうきぼでのたまき": 3953,
  "ちきゅうきぼでかんがえ": 4422,
  "ちきゅうきぼのもんだい": 4091,
  "ちきゅうきぼのおんだん": 1014,
  "ほう-ちきゅうのあるき": 3495,
  "ほう|ちきゅうのあるき": 1077,
  "うりぎょうのうちきかい": 1426,
  "きせきのほし、ちきゅう": 6167,
  "よしままちきたよしまじ": 1019,
  "こはざいにちきぎょうえ": 1154,
  "きてぃーえっちきもをた": 1737,
  "たくようかさいほうちき": 2275,
  "うちゅうからちきゅうに": 1262,
  "うちゅうからちきゅうを": 2866,
  "ちゅうからちきゅうをみ": 1629,
  "ちゅうからみたちきゅう": 3597,
  "じつぶつのそうみちきも": 1659,
  "しまひめいのち(いちき": 1043,
  "かわぐちきさぶろうさん": 2537,
  "かわぐちきょうのこちら": 2721,
  "しよしままちきたよしま": 1605,
  "しじちきほんじょうれい": 4390,
  "おびでんわのきちきょく": 4627,
  "おびでんわきちきょくの": 1556,
  "ひたちきょうせいしかい": 4327,
  "くらけんみきしぐちきち": 1493,
  "けんせつぎょうのうちき": 1555,
  "あくじゅんかんをたちき": 5934,
  "わくせいがちきゅうに衝": 1087,
  "あいはちきゅうをすくう": 13787,
  "あいちきゅうはく(あい": 2258,
  "あいちきゅうはくきねん": 5046,
  "といちきたくはたちょう": 1228,
  "じぞくかのうなちきゅう": 2434,
  "しんしょうひん「ちきん": 2353,
  "りょこうの「ちきゅうの": 1534,
  "りょこうのちきゅうのふ": 1016,
  "にちきょうどう】いらく": 1145,
  "にちきんむかのうなほう": 3317,
  "にちきんむじかんのわり": 1140,
  "にちきょういくをうけた": 1858,
  "にちきょういくをうけて": 1149,
  "にちきしゃかいけんし、": 2636,
  "にちきしゃかいけんした": 1301,
  "にちきんじょにようじで": 1098,
  "はるじゅうはちきっぷ」": 8669,
  "はるじゅうはちきっぷが": 2313,
  "はるじゅうはちきっぷさ": 1004,
  "はるじゅうはちきっぷで": 11239,
  "はるじゅうはちきっぷと": 1445,
  "はるじゅうはちきっぷに": 1470,
  "はるじゅうはちきっぷの": 13943,
  "はるじゅうはちきっぷは": 3766,
  "はるじゅうはちきっぷを": 7844,
  "もちきぎょうのことをど": 1172,
  "ごうようけん^たちきの": 1507,
  "がくふをいちきょくから": 10807,
  "ちきほんじょうれいにつ": 1286,
  "はまぐちきょうこあにま": 2811,
  "まんさいのちきゅうのふ": 1927,
  "ろせっちきょかしんせい": 1125,
  "かたみちきっぷのたび」": 1125,
  "いきものちきゅうおさむ": 1601,
  "たわひろしの『ちきゅう": 3167,
  "たあきひろの『ちきゅう": 1205,
  "まちきそくだいにごう)": 1059,
  "まちきんぺんのにんきれ": 1958,
  "まちきんゆうのせかいに": 1084,
  "はっしょうのちきねんひ": 1046,
  "じき・ちきゅうわくせい": 1136,
  "わたしたちは、ちきゅう": 1442,
  "たちきのばっさいのほう": 2120,
  "たちきのばっさいのきり": 2561,
  "たちきは、とうがいりつ": 2306,
  "とうほうちきんしくいき": 1057,
  "けいいどちきゅうかがく": 1202,
  "そうしないもりやまちき": 1107,
  "みどりのちきゅうねっと": 2057,
  "いどちきゅうかがくかん": 1200,
  "うつくしいちきゅうをこ": 1707,
  "はおととちきゅうのかい": 4964,
  "じちきほんじょうれい」": 2708,
  "じちきほんじょうれいが": 1313,
  "じちきほんじょうれいと": 1364,
  "じちきほんじょうれいに": 3554,
  "じちきほんじょうれいの": 6187,
  "じちきほんじょうれいは": 1279,
  "じちきほんじょうれいを": 3668,
  "くだりの「ちきゅうのふ": 1549,
  "きとちきょうかいせんな": 1800,
  "ふをいちきょくからかん": 10793,
  "かけんたかしましくちき": 1249,
  "あとのほし、ちきゅう(": 6088,
  "みちきみまろばくしょう": 3236,
  "みちきょうのじえいたい": 7682,
  "みちきょうせいしかへど": 4484,
  "のいちきたあだちぐんい": 3517,
  "さきもりのみちきょうの": 7682,
  "りゅういちきねんまんが": 1407,
  "はなれがかたみちきろ2": 1587,
  "でんか&あいえいちきっ": 2915,
  "でんわのきちきょくこん": 1558
}